mlflow_duckdb/__init__.py
mlflow_duckdb/client.py
mlflow_duckdb-0.1.2.dist-info/LICENCE
mlflow_duckdb-0.1.2.dist-info/METADATA
mlflow_duckdb-0.1.2.dist-info/WHEEL
mlflow_duckdb-0.1.2.dist-info/RECORD
