Metadata-Version: 2.3
Name: mlflow-duckdb
Version: 0.1.2
Summary: An MLflow plugin that integrates DuckDB as a backend for artifact and model tracking, enabling efficient, serverless experiment management with a lightweight, portable database engine.
Author: Hugo Carvalho
Author-email: hugodanielsilvacarvalho.hc@gmail.com
Requires-Python: >=3.9
Classifier: Programming Language :: Python :: 3
Classifier: Programming Language :: Python :: 3.9
Classifier: Programming Language :: Python :: 3.10
Classifier: Programming Language :: Python :: 3.11
Classifier: Programming Language :: Python :: 3.12
Classifier: Programming Language :: Python :: 3.13
Requires-Dist: duckdb (>1.0.0)
Requires-Dist: mlflow (>2.0.1)
